{
  "sections": {
    "main": {
      "type": "main-page",
      "disabled": true,
      "settings": {
        "full_width": false
      }
    },
    "3624f0f7-4918-4eab-8ae7-a15e51cf69a5": {
      "type": "background-video",
      "custom_css": [
        "h2 {font-family: bebas neue; letter-spacing: 1px;}"
      ],
      "settings": {
        "video": "https:\/\/cdn.shopify.com\/videos\/c\/o\/v\/27c543247ac24153a06405e09db1c117.mp4",
        "subheading": "",
        "title": "MEET CARLY BURNETT:",
        "title_size": 74,
        "title_size_mobile": 34,
        "use_h1": false,
        "text": "<p>The Radiant Force Behind TKEES<\/p>",
        "enlarge_text": true,
        "button_label_1": "",
        "button_url_1": "",
        "button_label_2": "",
        "button_url_2": "",
        "text_alignment": "center center",
        "height_desktop": 700,
        "height_mobile": 500,
        "full_width": true,
        "overlay_style": "shadow"
      }
    },
    "393a7d48-5a65-4792-9d0e-128382c3661e": {
      "type": "image-with-text-overlay",
      "disabled": true,
      "custom_css": [
        "h2 {font-family: bebas neue; letter-spacing: 1px; color: #333;}",
        "p {color: #333;}"
      ],
      "settings": {
        "image": "shopify:\/\/shop_images\/Artboard_1_2f4e0dd3-7e08-4076-8eff-a5c88e2c2f0a.jpg",
        "mobile_image": "shopify:\/\/shop_images\/our-founder-hero-1.jpg",
        "image_position": "center center",
        "mobile_image_position": "center center",
        "height": "adapt",
        "height_desktop": 700,
        "height_mobile": 600,
        "image_link": "",
        "subheading": "",
        "title": "Meet Carly Burnett:",
        "title_size": 48,
        "title_size_mobile": 28,
        "use_h1": false,
        "text": "<p>The Radiant Force Behind TKEES<\/p>",
        "enlarge_text": true,
        "button_label_1": "",
        "button_url_1": "",
        "button_label_2": "",
        "button_url_2": "",
        "text_alignment": "center left",
        "full_width": false,
        "mobile_overlay_under": true,
        "overlay_style": "no_background"
      }
    },
    "0a70291e-53e1-42ee-b17c-d8aaf98d5acc": {
      "type": "rich-text",
      "blocks": {
        "template--15976017559727__0a70291e-53e1-42ee-b17c-d8aaf98d5acc-heading-1": {
          "type": "heading",
          "settings": {
            "title": "Rich text",
            "use_h1": false
          }
        },
        "template--15976017559727__0a70291e-53e1-42ee-b17c-d8aaf98d5acc-text-1": {
          "type": "text",
          "settings": {
            "text": "<p>Use this text to share information about your store with your customers. Describe products, share announcements, or welcome customers to your store.<\/p>",
            "enlarge_text": true
          }
        }
      },
      "block_order": [
        "template--15976017559727__0a70291e-53e1-42ee-b17c-d8aaf98d5acc-heading-1",
        "template--15976017559727__0a70291e-53e1-42ee-b17c-d8aaf98d5acc-text-1"
      ],
      "disabled": true,
      "custom_css": [
        "h2 {font-family: bebas neue; font-size: 24px; letter-spacing: 1px; font-color: #333; margin-bottom: 10px;}"
      ],
      "settings": {
        "height": "small",
        "text_alignment": "left",
        "full_width": false,
        "use_alt_bg": false
      }
    },
    "664f9c1c-ccc9-4402-85a7-1bbf93544edb": {
      "type": "image-with-text",
      "custom_css": [
        "h2 {font-family: bebas neue; font-size: 24px; letter-spacing: 1px; font-color: #333; margin-bottom: 10px;}"
      ],
      "settings": {
        "image": "shopify:\/\/shop_images\/happiness-1.jpg",
        "image_2": "shopify:\/\/shop_images\/happiness-2.jpg",
        "image_width": 700,
        "subheading": "",
        "title": "Happiness Personified",
        "use_h1": false,
        "text": "<p>Carly is the very essence of happiness. <br\/>Her infectious laughter and adventurous spirit light up every room she enters.<\/p>",
        "button_label": "",
        "button_link": "",
        "button_style": "primary",
        "image_position": "left",
        "text_alignment": "left",
        "use_alt_bg": false
      }
    },
    "5899ddde-5456-4021-94bc-c3b5a62a6a80": {
      "type": "custom-row",
      "blocks": {
        "0406d08a-644c-46a8-a943-2be662e6cafe": {
          "type": "image",
          "settings": {
            "width": "three-quarters",
            "image": "shopify:\/\/shop_images\/Birth_final_V3.jpg",
            "image_position": "center center",
            "height": "adapt",
            "height_desktop": 400,
            "height_mobile": 1000,
            "subheading": "",
            "title": "",
            "text": "",
            "enlarge_text": false,
            "button_label": "",
            "image_link": "",
            "text_alignment": "center center",
            "mobile_overlay_under": false,
            "overlay_style": "shadow"
          }
        },
        "9180c8b9-cddf-4cdb-9e9d-9cce32d14d1f": {
          "type": "text",
          "settings": {
            "width": "three-quarters",
            "subheading": "",
            "title": "The Birth of TKEES",
            "text": "<p>At 29, Carly co-founded TKEES and attended trade shows with her 3-month old. Her dedication and passion are the pillars of TKEES.<\/p>",
            "button_label": "",
            "button_link": "",
            "button_style": "primary",
            "text_alignment": "left"
          }
        }
      },
      "block_order": [
        "0406d08a-644c-46a8-a943-2be662e6cafe",
        "9180c8b9-cddf-4cdb-9e9d-9cce32d14d1f"
      ],
      "custom_css": [
        "h2 {font-family: bebas neue; font-size: 24px; letter-spacing: 1px; font-color: #333; margin-bottom: 10px;}"
      ],
      "settings": {
        "alignment": "bottom"
      }
    },
    "a79f1128-39ec-4017-b9b5-3f1df1c40a47": {
      "type": "custom-row",
      "blocks": {
        "ab85fb9c-852f-41db-8b35-0f919650eaa0": {
          "type": "image",
          "settings": {
            "width": "three-quarters",
            "image": "shopify:\/\/shop_images\/adventure-1.jpg",
            "image_position": "center center",
            "height": "adapt",
            "height_desktop": 400,
            "height_mobile": 1000,
            "subheading": "",
            "title": "",
            "text": "",
            "enlarge_text": false,
            "button_label": "",
            "image_link": "",
            "text_alignment": "center center",
            "mobile_overlay_under": false,
            "overlay_style": "shadow"
          }
        },
        "a13d3eff-60fc-471f-beb7-2cd3dbf770a5": {
          "type": "text",
          "settings": {
            "width": "three-quarters",
            "subheading": "",
            "title": "Adventurous Spirit",
            "text": "<p>Carly believes in seizing every moment and living life to the fullest.  <\/p>",
            "button_label": "",
            "button_link": "",
            "button_style": "primary",
            "text_alignment": "left"
          }
        }
      },
      "block_order": [
        "ab85fb9c-852f-41db-8b35-0f919650eaa0",
        "a13d3eff-60fc-471f-beb7-2cd3dbf770a5"
      ],
      "disabled": true,
      "custom_css": [
        "h2 {font-family: bebas neue; font-size: 24px; letter-spacing: 1px; font-color: #333; margin-bottom: 10px;}"
      ],
      "settings": {
        "alignment": "bottom"
      }
    },
    "87521aed-e631-405e-97e8-230a0ec3ffca": {
      "type": "image-with-text",
      "disabled": true,
      "custom_css": [
        "h2 {font-family: bebas neue; font-size: 24px; letter-spacing: 1px; font-color: #333; margin-bottom: 10px;}"
      ],
      "settings": {
        "image": "shopify:\/\/shop_images\/tkees-birth-story-2.jpg",
        "image_2": "shopify:\/\/shop_images\/tkees-birth-story-1.jpg",
        "image_width": 700,
        "subheading": "",
        "title": "The Birth of Tkees",
        "use_h1": false,
        "text": "<p>At 29 Carly co-founded TKEES and attended trade shows with her 3-month-old. Her dedication and passion are the pillars of TKEES.<\/p>",
        "button_label": "",
        "button_link": "",
        "button_style": "primary",
        "image_position": "left",
        "text_alignment": "left",
        "use_alt_bg": false
      }
    },
    "bd7dba03-1929-42f7-ae21-726af3f3830a": {
      "type": "gallery",
      "blocks": {
        "template--15976017559727__bd7dba03-1929-42f7-ae21-726af3f3830a-image-1": {
          "type": "image",
          "settings": {
            "image": "shopify:\/\/shop_images\/carly-selfie-1.jpg",
            "alignment": "center center",
            "enlarge_image": false,
            "subheading": "",
            "title": "",
            "button_label": "",
            "link": "",
            "text_alignment": "bottom left",
            "show_text_below": false,
            "title_below": "Color name",
            "show_swatch": true
          }
        },
        "template--15976017559727__bd7dba03-1929-42f7-ae21-726af3f3830a-image-2": {
          "type": "image",
          "settings": {
            "image": "shopify:\/\/shop_images\/carly-selfie-7.jpg",
            "alignment": "center center",
            "enlarge_image": false,
            "subheading": "",
            "title": "",
            "button_label": "",
            "link": "",
            "text_alignment": "bottom left",
            "show_text_below": false,
            "title_below": "Color name",
            "show_swatch": true
          }
        },
        "template--15976017559727__bd7dba03-1929-42f7-ae21-726af3f3830a-image-3": {
          "type": "image",
          "settings": {
            "image": "shopify:\/\/shop_images\/carly-selfie-2.jpg",
            "alignment": "center center",
            "enlarge_image": false,
            "subheading": "",
            "title": "",
            "button_label": "",
            "link": "",
            "text_alignment": "bottom left",
            "show_text_below": false,
            "title_below": "Color name",
            "show_swatch": true
          }
        },
        "template--15976017559727__bd7dba03-1929-42f7-ae21-726af3f3830a-image-4": {
          "type": "image",
          "settings": {
            "image": "shopify:\/\/shop_images\/carly-selfie-6.jpg",
            "alignment": "center center",
            "enlarge_image": false,
            "subheading": "",
            "title": "",
            "button_label": "",
            "link": "",
            "text_alignment": "bottom left",
            "show_text_below": false,
            "title_below": "Color name",
            "show_swatch": true
          }
        }
      },
      "block_order": [
        "template--15976017559727__bd7dba03-1929-42f7-ae21-726af3f3830a-image-1",
        "template--15976017559727__bd7dba03-1929-42f7-ae21-726af3f3830a-image-2",
        "template--15976017559727__bd7dba03-1929-42f7-ae21-726af3f3830a-image-3",
        "template--15976017559727__bd7dba03-1929-42f7-ae21-726af3f3830a-image-4"
      ],
      "custom_css": [
        ".slick-slider-overlay-dots {fill: #ffffff;}"
      ],
      "settings": {
        "grid": 4,
        "desktop_image_height": 400,
        "height_override": false,
        "mobile_image_height": 450,
        "mobile_grid": false,
        "title_size": 30,
        "title_size_mobile": 22,
        "enable_margin": true,
        "enable_row_spacing": false,
        "full_width": false,
        "remove_horizontal_padding": false,
        "use_alt_bg": false,
        "enable_carousel": true,
        "overlay_style": "no_background",
        "button_style": "primary"
      }
    },
    "82a8b8b7-a2bc-49d4-9e3e-d4e3ae5007d1": {
      "type": "rich-text",
      "blocks": {
        "1879506b-80e0-470d-b625-8d2dff33e919": {
          "type": "heading",
          "settings": {
            "title": "Signature Style",
            "use_h1": false
          }
        },
        "template--15976017559727__82a8b8b7-a2bc-49d4-9e3e-d4e3ae5007d1-text-1": {
          "type": "text",
          "settings": {
            "text": "<p>Casual, and chic are distinctly Carly. Her elevated tomboy aesthetic inspires her work and carries into her designs.<\/p>",
            "enlarge_text": false
          }
        }
      },
      "block_order": [
        "1879506b-80e0-470d-b625-8d2dff33e919",
        "template--15976017559727__82a8b8b7-a2bc-49d4-9e3e-d4e3ae5007d1-text-1"
      ],
      "custom_css": [
        "h2 {font-family: bebas neue; font-size: 24px; letter-spacing: 1px; font-color: #333; margin-bottom: 10px;}",
        ".fully-spaced-row--small {margin-top: 20px;}"
      ],
      "settings": {
        "height": "small",
        "text_alignment": "left",
        "full_width": true,
        "use_alt_bg": false
      }
    },
    "65b0711d-ffb0-465f-977e-ff06997d8ac9": {
      "type": "custom-row",
      "blocks": {
        "5078818f-a5b2-40e3-99af-780e0140cb76": {
          "type": "image",
          "settings": {
            "width": "two-thirds",
            "image": "shopify:\/\/shop_images\/design-final-1.jpg",
            "image_position": "center center",
            "height": "adapt",
            "height_desktop": 380,
            "height_mobile": 200,
            "subheading": "",
            "title": "",
            "text": "",
            "enlarge_text": false,
            "button_label": "",
            "image_link": "",
            "text_alignment": "center center",
            "mobile_overlay_under": false,
            "overlay_style": "shadow"
          }
        },
        "e8bbf4d2-c440-4acc-acd3-d0a4f1aba0f7": {
          "type": "text",
          "settings": {
            "width": "third",
            "subheading": "",
            "title": "Design Philosophy",
            "text": "<p>Carly has a meticulous eye for detail. Her love for symmetry and minimalism shines through in every TKEES design.<\/p>",
            "button_label": "",
            "button_link": "",
            "button_style": "primary",
            "text_alignment": "left"
          }
        }
      },
      "block_order": [
        "5078818f-a5b2-40e3-99af-780e0140cb76",
        "e8bbf4d2-c440-4acc-acd3-d0a4f1aba0f7"
      ],
      "custom_css": [
        "h2 {font-family: bebas neue; font-size: 24px; letter-spacing: 1px; font-color: #333; margin-bottom: 10px;}"
      ],
      "settings": {
        "alignment": "middle"
      }
    },
    "83b496a1-cfb0-41d4-b56b-92f914e0bb1a": {
      "type": "custom-row",
      "blocks": {
        "d50abee6-8223-43a8-b347-c25eba372255": {
          "type": "image",
          "settings": {
            "width": "half",
            "image": "shopify:\/\/shop_images\/generous-1.jpg",
            "image_position": "center center",
            "height": "adapt",
            "height_desktop": 400,
            "height_mobile": 1000,
            "subheading": "",
            "title": "",
            "text": "",
            "enlarge_text": false,
            "button_label": "",
            "image_link": "",
            "text_alignment": "center center",
            "mobile_overlay_under": false,
            "overlay_style": "shadow"
          }
        },
        "4af695b8-baa7-4e41-b4d2-06baeadeec4c": {
          "type": "text",
          "settings": {
            "width": "third",
            "subheading": "",
            "title": "Generous Soul",
            "text": "<p>More than style and design, Carly's generosity and caring nature make her stand out. She ensures everyone around her feels valued and happy :)<\/p>",
            "button_label": "",
            "button_link": "",
            "button_style": "primary",
            "text_alignment": "left"
          }
        },
        "50ff2f5d-7e7f-4b09-b5db-65e8cad9e4b4": {
          "type": "text",
          "settings": {
            "width": "half",
            "subheading": "",
            "title": "",
            "text": "",
            "button_label": "EXPLORE TKEES",
            "button_link": "https:\/\/tkees.com\/",
            "button_style": "primary",
            "text_alignment": "center"
          }
        }
      },
      "block_order": [
        "d50abee6-8223-43a8-b347-c25eba372255",
        "4af695b8-baa7-4e41-b4d2-06baeadeec4c",
        "50ff2f5d-7e7f-4b09-b5db-65e8cad9e4b4"
      ],
      "custom_css": [
        "h2 {font-family: bebas neue; font-size: 24px; letter-spacing: 1px; font-color: #333; margin-bottom: 10px;}",
        ".btn--primary {font-family: bebas neue; font-size: 16px; letter-spacing: 1px; padding: 0.9em 50px 0.9em;}"
      ],
      "settings": {
        "alignment": "middle"
      }
    }
  },
  "order": [
    "main",
    "3624f0f7-4918-4eab-8ae7-a15e51cf69a5",
    "393a7d48-5a65-4792-9d0e-128382c3661e",
    "0a70291e-53e1-42ee-b17c-d8aaf98d5acc",
    "664f9c1c-ccc9-4402-85a7-1bbf93544edb",
    "5899ddde-5456-4021-94bc-c3b5a62a6a80",
    "a79f1128-39ec-4017-b9b5-3f1df1c40a47",
    "87521aed-e631-405e-97e8-230a0ec3ffca",
    "bd7dba03-1929-42f7-ae21-726af3f3830a",
    "82a8b8b7-a2bc-49d4-9e3e-d4e3ae5007d1",
    "65b0711d-ffb0-465f-977e-ff06997d8ac9",
    "83b496a1-cfb0-41d4-b56b-92f914e0bb1a"
  ]
}
